powerranger/__init__.py
powerranger/powerranger.py
tests/__init__.py
powerranger-0.0.1.dist-info/LICENSE
powerranger-0.0.1.dist-info/METADATA
powerranger-0.0.1.dist-info/WHEEL
powerranger-0.0.1.dist-info/top_level.txt
powerranger-0.0.1.dist-info/RECORD
