Metadata-Version: 2.1
Name: powerranger
Version: 0.0.1
Summary: lf
Home-page: https://github.com/clayboone/powerranger.git
Author: Clay Boone
Author-email: tener.hades@gmail.com
License: UNKNOWN
Platform: UNKNOWN
Classifier: Programming Language :: Python :: 3
Classifier: License :: OSI Approved :: MIT License
Classifier: Operating System :: Microsoft :: Windows
Requires-Python: >=3.8
